leea_agent_sdk/__init__.py
leea_agent_sdk/agent.py
leea_agent_sdk/api.py
leea_agent_sdk/context.py
leea_agent_sdk/logger.py
leea_agent_sdk/runtime.py
leea_agent_sdk/transport.py
leea_agent_sdk/web3_evm.py
leea_agent_sdk/web3_solana.py
leea_agent_sdk/registry-client/.gitignore
leea_agent_sdk/registry-client/registry-client-linux-aarch64
leea_agent_sdk/registry-client/registry-client-linux-x86_64
leea_agent_sdk/registry-client/registry-client-macos-aarch64
leea_agent_sdk/registry-client/registry-client-macos-x86_64
leea_agent_sdk-0.0.6.dist-info/METADATA
leea_agent_sdk-0.0.6.dist-info/WHEEL
leea_agent_sdk-0.0.6.dist-info/RECORD
