Metadata-Version: 2.4
Name: leea_agent_sdk
Version: 0.0.6
Summary: Leea agent SDK
Project-URL: Homepage, https://github.com/Leea-Labs/leea-agent-sdk-python
Project-URL: Documentation, https://github.com/Leea-Labs/leea-agent-sdk-python/blob/main/README.md
Project-URL: Repository, https://github.com/Leea-Labs/leea-agent-sdk-python
License-Expression: MIT
Keywords: agents,leea,sdk
Requires-Python: >=3.9
Requires-Dist: base58==2.1.1
Requires-Dist: certifi~=2023.5.7
Requires-Dist: eth-account~=0.13.4
Requires-Dist: eth-utils~=5.2.0
Requires-Dist: jsonschema~=4.23.0
Requires-Dist: protobuf~=5.29.3
Requires-Dist: pydantic~=2.9.2
Requires-Dist: solana~=0.36.2
Requires-Dist: solders~=0.23.0
Requires-Dist: urllib3~=2.2.3
Requires-Dist: web3[tester]~=7.7.0
Requires-Dist: websockets~=13.1
